markdown_to_slack_mkdown/__init__.py
markdown_to_slack_mkdown/_version.py
markdown_to_slack_mkdown/converter.py
markdown_to_slack_mkdown-0.1.3.dist-info/licenses/LICENSE
markdown_to_slack_mkdown-0.1.3.dist-info/METADATA
markdown_to_slack_mkdown-0.1.3.dist-info/WHEEL
markdown_to_slack_mkdown-0.1.3.dist-info/top_level.txt
markdown_to_slack_mkdown-0.1.3.dist-info/RECORD
