Metadata-Version: 2.4
Name: markdown-to-slack-mkdown
Version: 0.1.3
Summary: Convert GitHub markdown to Slack markdown format
Home-page: https://github.com/eritikass/markdown-to-slack-mkdown
Author: Siim Tiilen
Author-email: Your Name <your.email@example.com>
License: MIT
Classifier: Development Status :: 4 - Beta
Classifier: Intended Audience :: Developers
Classifier: Topic :: Software Development :: Libraries :: Python Modules
Classifier: License :: OSI Approved :: MIT License
Classifier: Programming Language :: Python :: 3
Classifier: Programming Language :: Python :: 3.12
Classifier: Programming Language :: Python :: 3.13
Requires-Python: >=3.12
License-File: LICENSE
Dynamic: author
Dynamic: home-page
Dynamic: license-file
Dynamic: requires-python
